genro_bag/__init__.py
genro_bag/bag.py
genro_bag/bag_parse.py
genro_bag/bag_query.py
genro_bag/bag_serialize.py
genro_bag/bagnode.py
genro_bag/builder.py
genro_bag/py.typed
genro_bag/resolver.py
genro_bag/builders/README.md
genro_bag/builders/__init__.py
genro_bag/builders/html/__init__.py
genro_bag/builders/html/html5_schema.bag.json
genro_bag/builders/html/html5_schema.bag.mp
genro_bag/builders/html/html_builder.py
genro_bag/builders/markdown/__init__.py
genro_bag/builders/markdown/markdown_builder.py
genro_bag/builders/xsd/__init__.py
genro_bag/builders/xsd/xsd_builder.py
genro_bag/builders/xsd/xsd_reader.py
genro_bag/resolvers/__init__.py
genro_bag/resolvers/directory_resolver.py
genro_bag/resolvers/openapi_resolver.py
genro_bag/resolvers/url_resolver.py
genro_bag-0.7.6.dist-info/METADATA
genro_bag-0.7.6.dist-info/WHEEL
genro_bag-0.7.6.dist-info/licenses/LICENSE
genro_bag-0.7.6.dist-info/licenses/NOTICE
genro_bag-0.7.6.dist-info/RECORD
