Metadata-Version: 2.4
Name: genro-bag
Version: 0.7.6
Summary: Modernized bag system for the Genropy framework - hierarchical data container with XML serialization
Project-URL: Homepage, https://github.com/genropy/genro-bag
Project-URL: Documentation, https://genro-bag.readthedocs.io
Project-URL: Repository, https://github.com/genropy/genro-bag
Project-URL: Issues, https://github.com/genropy/genro-bag/issues
Author: Genropy Team
License-Expression: Apache-2.0
License-File: LICENSE
License-File: NOTICE
Keywords: bag,data-container,genro,genropy,hierarchical-data,xml-serialization
Classifier: Development Status :: 4 - Beta
Classifier: Intended Audience :: Developers
Classifier: Operating System :: OS Independent
Classifier: Programming Language :: Python :: 3
Classifier: Programming Language :: Python :: 3.10
Classifier: Programming Language :: Python :: 3.11
Classifier: Programming Language :: Python :: 3.12
Classifier: Programming Language :: Python :: 3.13
Classifier: Topic :: Software Development :: Libraries :: Python Modules
Classifier: Typing :: Typed
Requires-Python: >=3.10
Requires-Dist: genro-toolbox>=0.6.1
Requires-Dist: genro-tytx>=0.1.0
Provides-Extra: all
Requires-Dist: httpx>=0.27.0; extra == 'all'
Requires-Dist: msgpack>=1.0; extra == 'all'
Requires-Dist: mypy>=1.0; extra == 'all'
Requires-Dist: myst-parser>=4.0.0; extra == 'all'
Requires-Dist: orjson>=3.9; extra == 'all'
Requires-Dist: pytest-asyncio>=0.23.0; extra == 'all'
Requires-Dist: pytest-cov>=4.0; extra == 'all'
Requires-Dist: pytest>=7.0; extra == 'all'
Requires-Dist: ruff>=0.1.0; extra == 'all'
Requires-Dist: sphinx-autodoc-typehints>=3.0.0; extra == 'all'
Requires-Dist: sphinx-rtd-theme>=3.0.0; extra == 'all'
Requires-Dist: sphinx>=8.0.0; extra == 'all'
Requires-Dist: sphinxcontrib-mermaid>=1.0.0; extra == 'all'
Requires-Dist: xmlschema>=3.0; extra == 'all'
Provides-Extra: dev
Requires-Dist: httpx>=0.27.0; extra == 'dev'
Requires-Dist: msgpack>=1.0; extra == 'dev'
Requires-Dist: mypy>=1.0; extra == 'dev'
Requires-Dist: orjson>=3.9; extra == 'dev'
Requires-Dist: pytest-asyncio>=0.23.0; extra == 'dev'
Requires-Dist: pytest-cov>=4.0; extra == 'dev'
Requires-Dist: pytest>=7.0; extra == 'dev'
Requires-Dist: ruff>=0.1.0; extra == 'dev'
Provides-Extra: docs
Requires-Dist: myst-parser>=4.0.0; extra == 'docs'
Requires-Dist: sphinx-autodoc-typehints>=3.0.0; extra == 'docs'
Requires-Dist: sphinx-rtd-theme>=3.0.0; extra == 'docs'
Requires-Dist: sphinx>=8.0.0; extra == 'docs'
Requires-Dist: sphinxcontrib-mermaid>=1.0.0; extra == 'docs'
Provides-Extra: xsd-validate
Requires-Dist: xmlschema>=3.0; extra == 'xsd-validate'
